mesh_database_client/__init__.py
mesh_database_client/database.py
mesh_database_client-1.3.dist-info/METADATA
mesh_database_client-1.3.dist-info/WHEEL
mesh_database_client-1.3.dist-info/top_level.txt
mesh_database_client-1.3.dist-info/RECORD
